code_chunker/__init__.py
code_chunker/__version__.py
code_chunker/chunker.py
code_chunker/config.py
code_chunker/error_recovery.py
code_chunker/exceptions.py
code_chunker/incremental.py
code_chunker/models.py
code_chunker/parser.py
code_chunker/languages/__init__.py
code_chunker/languages/base.py
code_chunker/languages/go.py
code_chunker/languages/javascript.py
code_chunker/languages/python.py
code_chunker/languages/rust.py
code_chunker/languages/solidity.py
code_chunker/languages/typescript.py
code_chunker/strategies/__init__.py
code_chunker/strategies/base.py
code_chunker/strategies/default.py
code_chunker/strategies/semantic.py
code_chunker/utils/__init__.py
code_chunker/utils/file_utils.py
code_chunker/utils/validators.py
code_chunker-1.3.2.dist-info/licenses/LICENSE
tests/__init__.py
tests/conftest.py
tests/test_chunker.py
tests/test_incremental.py
tests/test_parser.py
code_chunker-1.3.2.dist-info/METADATA
code_chunker-1.3.2.dist-info/WHEEL
code_chunker-1.3.2.dist-info/top_level.txt
code_chunker-1.3.2.dist-info/RECORD
