Metadata-Version: 2.4
Name: code-chunker
Version: 1.3.2
Summary: A pragmatic multi-language code parser optimized for LLM applications
Home-page: https://github.com/JimAiMoment/code-chunker
Author: Jim Fang
Author-email: Jim Fang <jimthebeacon@gmail.com>
License: MIT
Classifier: Development Status :: 3 - Alpha
Classifier: Intended Audience :: Developers
Classifier: License :: OSI Approved :: MIT License
Classifier: Programming Language :: Python :: 3
Classifier: Programming Language :: Python :: 3.11
Classifier: Programming Language :: Python :: 3.12
Classifier: Programming Language :: Python :: 3.13
Classifier: Programming Language :: Python :: 3.14
Requires-Python: >=3.11
License-File: LICENSE
Dynamic: author
Dynamic: home-page
Dynamic: license-file
Dynamic: requires-python
